syngenta_digital_alc/__init__.py
syngenta_digital_alc/apigateway/__init__.py
syngenta_digital_alc/apigateway/custom_exceptions.py
syngenta_digital_alc/apigateway/handler_requirements.py
syngenta_digital_alc/apigateway/request_client.py
syngenta_digital_alc/apigateway/request_validator.py
syngenta_digital_alc/apigateway/response_client.py
syngenta_digital_alc/apigateway/router.py
syngenta_digital_alc/apigateway/error_handling/__init__.py
syngenta_digital_alc/apigateway/error_handling/timeout.py
syngenta_digital_alc/common/__init__.py
syngenta_digital_alc/common/json_helper.py
syngenta_digital_alc/common/logger.py
syngenta_digital_alc/common/troubleshoot_decorator.py
syngenta_digital_alc/dynamodb/__init__.py
syngenta_digital_alc/dynamodb/event_client.py
syngenta_digital_alc/dynamodb/handler_requirements.py
syngenta_digital_alc/dynamodb/record_client.py
syngenta_digital_alc/generic/__init__.py
syngenta_digital_alc/generic/event_client.py
syngenta_digital_alc/generic/handler_requirements.py
syngenta_digital_alc/s3/__init__.py
syngenta_digital_alc/s3/event_client.py
syngenta_digital_alc/s3/handler_requirements.py
syngenta_digital_alc/s3/record_client.py
syngenta_digital_alc/sns/__init__.py
syngenta_digital_alc/sns/event_client.py
syngenta_digital_alc/sns/handler_requirements.py
syngenta_digital_alc/sns/record_client.py
syngenta_digital_alc/sqs/__init__.py
syngenta_digital_alc/sqs/event_client.py
syngenta_digital_alc/sqs/handler_requirements.py
syngenta_digital_alc/sqs/record_client.py
tests/__init__.py
tests/syngenta_digital_alc/__init__.py
tests/syngenta_digital_alc/apigateway/__init__.py
tests/syngenta_digital_alc/apigateway/mock_before_all.py
tests/syngenta_digital_alc/apigateway/mock_data.py
tests/syngenta_digital_alc/apigateway/mock_handler.py
tests/syngenta_digital_alc/apigateway/test_handler_decorator.py
tests/syngenta_digital_alc/apigateway/test_request_client.py
tests/syngenta_digital_alc/apigateway/test_request_validator.py
syngenta_digital_alc-1.28.dist-info/LICENSE
syngenta_digital_alc-1.28.dist-info/METADATA
syngenta_digital_alc-1.28.dist-info/WHEEL
syngenta_digital_alc-1.28.dist-info/top_level.txt
syngenta_digital_alc-1.28.dist-info/RECORD
