Metadata-Version: 2.1
Name: syngenta-digital-alc
Version: 1.28
Summary: DRY approach to working with AWS Lambdas
Home-page: https://github.com/syngenta-digital/alc-python.git
Author: Paul Cruse III, Technical Lead, Syngenta Digital
Author-email: paul.cruse@syngenta.com
Classifier: Environment :: Web Environment
Classifier: Intended Audience :: Developers
Classifier: Topic :: Internet :: WWW/HTTP :: Dynamic Content
Classifier: Topic :: Software Development :: Libraries :: Python Modules
Classifier: Programming Language :: Python
Classifier: Programming Language :: Python :: 2
Classifier: Programming Language :: Python :: 2.7
Classifier: Programming Language :: Python :: 3
Classifier: Programming Language :: Python :: 3.6
Classifier: Programming Language :: Python :: 3.7
Requires-Python: >=3.0
License-File: LICENSE
Requires-Dist: dynamodb-json
Requires-Dist: jsonschema
Requires-Dist: jsonpickle
Requires-Dist: jsonref
Requires-Dist: pyyaml
